shholiday/__init__.py
shholiday/holiday2020.py
shholiday-0.0.1.dist-info/LICENSE
shholiday-0.0.1.dist-info/METADATA
shholiday-0.0.1.dist-info/WHEEL
shholiday-0.0.1.dist-info/top_level.txt
shholiday-0.0.1.dist-info/RECORD
