Metadata-Version: 2.1
Name: shholiday
Version: 0.0.1
Summary: Check if the current date is a holiday in Korea.
Home-page: https://github.com/league3236/shholiday
Author: league3236
Author-email: league3236@gmail.com
License: MIT
Platform: UNKNOWN
Classifier: Programming Language :: Python :: 3
Classifier: License :: OSI Approved :: MIT License
Classifier: Operating System :: OS Independent
Requires-Python: >=3.6
